Metadata-Version: 2.4
Name: tachtech-panther-sdk
Version: 0.1.0
Summary: Python SDK for Panther Security - API Client, Detection Framework, and SPL Converter
Author: TachTech Engineering
License: MIT
Project-URL: Homepage, https://github.com/TachTech-Engineering/panther_sdk
Project-URL: Repository, https://github.com/TachTech-Engineering/panther_sdk
Project-URL: Issues, https://github.com/TachTech-Engineering/panther_sdk/issues
Keywords: panther,security,siem,detection,sdk,splunk,spl,converter
Classifier: Development Status :: 4 - Beta
Classifier: Intended Audience :: Developers
Classifier: License :: OSI Approved :: MIT License
Classifier: Programming Language :: Python :: 3
Classifier: Programming Language :: Python :: 3.9
Classifier: Programming Language :: Python :: 3.10
Classifier: Programming Language :: Python :: 3.11
Classifier: Programming Language :: Python :: 3.12
Classifier: Topic :: Security
Requires-Python: >=3.9
Requires-Dist: httpx>=0.25.0
Requires-Dist: pydantic>=2.0.0
Requires-Dist: python-dotenv>=1.0.0
Requires-Dist: typing-extensions>=4.0.0
Provides-Extra: dev
Requires-Dist: pytest>=7.0.0; extra == "dev"
Requires-Dist: pytest-asyncio>=0.21.0; extra == "dev"
Requires-Dist: pytest-cov>=4.0.0; extra == "dev"
Requires-Dist: respx>=0.20.0; extra == "dev"
Requires-Dist: ruff>=0.1.0; extra == "dev"
Requires-Dist: mypy>=1.0.0; extra == "dev"
